.pylintrc
.travis.yml
AUTHORS
ChangeLog
MANIFEST.in
README.rst
demo.org
preso.org
requirements.txt
setup.cfg
setup.py
tox.ini
tests/test_main.py
wgstatus/__init__.py
wgstatus/main.py
wgstatus/rest.py
wgstatus.egg-info/PKG-INFO
wgstatus.egg-info/SOURCES.txt
wgstatus.egg-info/dependency_links.txt
wgstatus.egg-info/entry_points.txt
wgstatus.egg-info/not-zip-safe
wgstatus.egg-info/pbr.json
wgstatus.egg-info/requires.txt
wgstatus.egg-info/top_level.txt