Metadata-Version: 1.0
Name: wgstatus
Version: 1.3.0
Summary: UNKNOWN
Home-page: https://github.com/choppsv1/wgstatus
Author: Christian Hopps
Author-email: chopps@gmail.com
License: Apache-2
Platform: UNKNOWN
